Metadata-Version: 2.4
Name: DashingTurtle
Version: 0.1.19
Summary: An applicaton for building structural landscapes of RNA sequence modifications with Nanopore data.
Home-page: https://github.com/jwbear/Dashing_Turtle.git
Author: J. White Bear
Author-email: jwbear15@gmail.com
Classifier: Programming Language :: Python :: 3
Classifier: License :: OSI Approved :: MIT License
Classifier: Operating System :: OS Independent
Requires-Python: >=3.7
Requires-Dist: aiofiles==24.1.0
Requires-Dist: asttokens==3.0.0
Requires-Dist: bcrypt==4.3.0
Requires-Dist: cffi==2.0.0b1
Requires-Dist: colorama==0.4.6
Requires-Dist: colour==0.1.5
Requires-Dist: contourpy==1.2.1
Requires-Dist: cryptography==43.0.3
Requires-Dist: cycler==0.12.1
Requires-Dist: decorator==5.1.1
Requires-Dist: Deprecated==1.2.18
Requires-Dist: dict-toolbox==5.0.0
Requires-Dist: dotenv==0.9.9
Requires-Dist: drawsvg==2.4.0
Requires-Dist: executing==2.0.1
Requires-Dist: filelock==3.14.0
Requires-Dist: fonttools==4.51.0
Requires-Dist: fsspec==2024.5.0
Requires-Dist: greenlet==3.1.1
Requires-Dist: iniconfig==2.1.0
Requires-Dist: ipython==8.26.0
Requires-Dist: jedi==0.19.1
Requires-Dist: Jinja2==3.1.6
Requires-Dist: joblib==1.4.2
Requires-Dist: kiwisolver==1.4.5
Requires-Dist: kmodes==0.12.2
Requires-Dist: lazy-object-proxy==1.11.0
Requires-Dist: mariadb==1.1.10
Requires-Dist: markdown-it-py==3.0.0
Requires-Dist: MarkupSafe==3.0.2
Requires-Dist: matplotlib==3.9.0
Requires-Dist: matplotlib-inline==0.1.7
Requires-Dist: matplotlib-venn==1.1.1
Requires-Dist: mdurl==0.1.2
Requires-Dist: mpmath==1.3.0
Requires-Dist: msgpack==1.1.1
Requires-Dist: mysql-connector==2.2.9
Requires-Dist: nest-asyncio==1.6.0
Requires-Dist: networkx==3.3
Requires-Dist: numpy==1.26.4
Requires-Dist: packaging==24.0
Requires-Dist: pandas==2.2.2
Requires-Dist: paramiko==3.5.0
Requires-Dist: parso==0.8.4
Requires-Dist: pexpect==4.9.0
Requires-Dist: pillow==10.3.0
Requires-Dist: platformdirs==4.2.2
Requires-Dist: pluggy==1.6.0
Requires-Dist: prompt_toolkit==3.0.47
Requires-Dist: ptyprocess==0.7.0
Requires-Dist: pure_eval==0.2.3
Requires-Dist: pycparser==2.22
Requires-Dist: Pygments==2.19.2
Requires-Dist: PyMySQL==1.1.1
Requires-Dist: PyNaCl==1.5.0
Requires-Dist: pyparsing==3.1.2
Requires-Dist: PyQt6==6.9.0
Requires-Dist: PyQt6-Qt6==6.9.1
Requires-Dist: PyQt6_sip==13.10.2
Requires-Dist: pysam==0.23.0
Requires-Dist: pytest==8.4.1
Requires-Dist: python-dateutil==2.9.0.post0
Requires-Dist: python-dotenv==1.1.1
Requires-Dist: pytz==2024.1
Requires-Dist: PyWavelets==1.8.0
Requires-Dist: PyYAML==6.0.2
Requires-Dist: rend==7.0.2
Requires-Dist: rich==14.0.0
Requires-Dist: scikit-learn==1.4.2
Requires-Dist: scipy==1.13.0
Requires-Dist: seaborn==0.13.2
Requires-Dist: six==1.16.0
Requires-Dist: sniffio==1.3.1
Requires-Dist: snowflake-id==1.0.2
Requires-Dist: SQLAlchemy==2.0.42
Requires-Dist: sshtunnel==0.4.0
Requires-Dist: stack-data==0.6.3
Requires-Dist: svgpathtools==1.6.1
Requires-Dist: svgwrite==1.4.3
Requires-Dist: sympy==1.12.1
Requires-Dist: threadpoolctl==3.5.0
Requires-Dist: toml==0.10.2
Requires-Dist: torch==2.2.2
Requires-Dist: traitlets==5.14.3
Requires-Dist: typing_extensions==4.12.1
Requires-Dist: tzdata==2024.1
Requires-Dist: varnaapi==1.2.0
Requires-Dist: wcwidth==0.2.13
Requires-Dist: wrapt==1.16.0
Dynamic: author
Dynamic: author-email
Dynamic: classifier
Dynamic: description
Dynamic: description-content-type
Dynamic: home-page
Dynamic: requires-dist
Dynamic: requires-python
Dynamic: summary
